{
    "@id": "people:p911190",
    "bioc:has_family_relation": [
        {
            "@id": "ns1:p1902448314948578170"
        },
        {
            "@id": "ns1:p1487656207991674466"
        }
    ],
    "skos:hiddenLabel": {
        "@language": "fi",
        "@value": "Paasivuori, Tyyne Maria"
    },
    "sch:relatedLink": {
        "@id": "mps:911190.aspx"
    },
    "semparl:representative_period": [
        {
            "@id": "times:t_1962-02-20_1962-02-20_1974-07-28_1974-07-28"
        },
        {
            "@id": "times:t_1954-03-29_1954-03-29_1958-07-21_1958-07-21"
        }
    ],
    "semparl:occupation_text": {
        "@language": "fi",
        "@value": "sosionomi, kirjaltaja"
    },
    "semparl:end_of_representative_period_text": "28.07.1974",
    "semparl:end_of_representative_period": {
        "@id": "times:t___1974-07-28_1974-07-28"
    },
    "bioc:has_occupation": [
        {
            "@id": "occupations:o102"
        },
        {
            "@id": "occupations:o1210"
        }
    ],
    "semparl:has_party_membership": {
        "@id": "event:p2483676736375695341"
    },
    "crm:P100i_died_in": {
        "@id": "event:d911190"
    },
    "xl:altLabel": {
        "@id": "label:l1047619166822317304"
    },
    "xl:prefLabel": {
        "@id": "label:l2694673749935467456"
    },
    "dct:source": {
        "@id": "https://avoindata.eduskunta.fi/api/v1/tables/MemberOfParliament/rows?perPage=10&page=0&columnName=personId&columnValue=911190"
    },
    "semparl:sortingLabel": "paasivuori tyyne",
    "bioc:has_gender": {
        "@id": "sch:Female"
    },
    "crm:P98i_was_born": {
        "@id": "event:b911190"
    },
    "sch:image": {
        "@id": "http://commons.wikimedia.org/wiki/Special:FilePath/Tyyne%20Paasivuori.png"
    },
    "sch:sameAs": [
        {
            "@id": "mps:911190.aspx"
        },
        {
            "@id": "https://fi.wikipedia.org/wiki/Tyyne_Paasivuori"
        },
        {
            "@id": "wd:Q17382755"
        }
    ],
    "semparl:has_education": [
        {
            "@id": "event:e2721911473156460576"
        },
        {
            "@id": "event:e2299350954229651398"
        },
        {
            "@id": "event:e2161964369493430975"
        },
        {
            "@id": "event:e9482666691503444097"
        },
        {
            "@id": "event:e3045036212637843797"
        }
    ],
    "bioc:bearer_of": [
        {
            "@id": "event:e2181435952199773827"
        },
        {
            "@id": "event:e2172215209778571052"
        },
        {
            "@id": "event:e1635781955792618774"
        },
        {
            "@id": "event:e1765022184589694229"
        },
        {
            "@id": "event:e5058974148844575051"
        },
        {
            "@id": "event:e1833900554551623917"
        },
        {
            "@id": "event:e6251487375680136482"
        },
        {
            "@id": "event:e7135963663790736382"
        },
        {
            "@id": "event:e2524685946895446215"
        },
        {
            "@id": "event:e2192718098525877608"
        },
        {
            "@id": "event:e3358507820660535464"
        },
        {
            "@id": "event:e9154082852751947523"
        },
        {
            "@id": "event:e5511160373317955219"
        },
        {
            "@id": "event:e2104932031898251028"
        },
        {
            "@id": "event:e2004750753990910964"
        },
        {
            "@id": "event:e1207388068773043710"
        },
        {
            "@id": "event:e1881126623261808246"
        },
        {
            "@id": "event:e2708630843964981518"
        },
        {
            "@id": "event:e1189405880553925803"
        },
        {
            "@id": "event:e1901693318649257658"
        },
        {
            "@id": "event:e2748636787044602515"
        },
        {
            "@id": "event:e2276618781371893101"
        },
        {
            "@id": "event:e1265240205908877966"
        },
        {
            "@id": "event:e6380006027382380844"
        },
        {
            "@id": "event:e4393857686613533373"
        },
        {
            "@id": "event:e3046896685202896739"
        },
        {
            "@id": "event:e1063609031807402428"
        },
        {
            "@id": "event:e1900195670117063717"
        },
        {
            "@id": "event:e2658665181778955749"
        },
        {
            "@id": "event:e1641885244201610766"
        },
        {
            "@id": "event:e3058265575527688142"
        },
        {
            "@id": "event:e1664481113923510346"
        },
        {
            "@id": "event:e1589234674144052840"
        },
        {
            "@id": "event:e6801120323859157668"
        },
        {
            "@id": "event:e2030296170743965606"
        },
        {
            "@id": "event:e2455386276424059843"
        },
        {
            "@id": "event:e1867337394518953235"
        },
        {
            "@id": "event:e7153958423855037393"
        },
        {
            "@id": "event:e2953132644244853047"
        },
        {
            "@id": "event:e2968820093402769589"
        },
        {
            "@id": "event:e2311793686701774611"
        },
        {
            "@id": "event:e1700875958246746538"
        },
        {
            "@id": "event:e9430217490338078804"
        },
        {
            "@id": "event:e1718090082154017429"
        },
        {
            "@id": "event:e2904452670921937962"
        }
    ],
    "@type": "bioc:Person",
    "skos:prefLabel": {
        "@language": "fi",
        "@value": "Paasivuori, Tyyne (1907-1974)"
    },
    "skos:altLabel": {
        "@language": "fi",
        "@value": "Paasivuori, Tyyne Maria"
    },
    "semparl:party": {
        "@id": "groups:Q499029"
    },
    "semparl:id": "911190",
    "@context": {
        "owl": "http://www.w3.org/2002/07/owl#",
        "skos": "http://www.w3.org/2004/02/skos/core#",
        "nif": "http://persistence.uni-leipzig.org/nlp2rdf/ontologies/nif-core#",
        "eks": "http://ldf.fi/eks/",
        "ns1": "http://ldf.fi/semparl/relations/",
        "spls": "http://ldf.fi/schema/semparl/linguistics/",
        "twitter": "https://twitter.com/",
        "yso": "http://www.yso.fi/onto/yso/",
        "dcterms": "http://purl.org/dc/terms/",
        "sch": "http://schema.org/",
        "text": "http://jena.apache.org/text#",
        "spatial": "http://jena.apache.org/spatial#",
        "portal": "http://ldf.fi/schema/parliamentsampo-portal/",
        "foaf": "http://xmlns.com/foaf/0.1/",
        "item": "http://ldf.fi/semparl/items/",
        "void": "http://rdfs.org/ns/void#",
        "committees": "http://ldf.fi/semparl/groups/committees/",
        "eterms": "http://ldf.fi/semparl/times/electoral-terms/",
        "ekss": "http://ldf.fi/schema/eks/",
        "viaf": "https://viaf.org/viaf/",
        "geo1": "http://www.w3.org/2003/01/geo/wgs84_pos#",
        "mps": "https://www.eduskunta.fi/FI/kansanedustajat/Sivut/",
        "external": "http://ldf.fi/semparl/external/",
        "geosparql": "http://www.opengis.net/ont/geosparql#",
        "yle": "https://yle.fi/aihe/t/",
        "semparl_linguistics": "http://ldf.fi/schema/semparl/linguistics/",
        "sps": "http://ldf.fi/semparl/speeches/",
        "semparls": "http://ldf.fi/schema/semparl/",
        "semparl": "http://ldf.fi/schema/semparl/",
        "finaf": "http://urn.fi/URN:NBN:fi:au:finaf:",
        "roles": "http://ldf.fi/semparl/roles/",
        "xsd": "http://www.w3.org/2001/XMLSchema#",
        "districts": "http://ldf.fi/semparl/groups/districts/",
        "affiliations": "http://ldf.fi/semparl/affiliations/",
        "rdfs": "http://www.w3.org/2000/01/rdf-schema#",
        "occupations": "http://ldf.fi/semparl/occupations/",
        "wd": "http://www.wikidata.org/entity/",
        "geo": "http://www.w3.org/2003/01/geo/wgs84_pos#",
        "sd": "http://www.w3.org/ns/sparql-service-description#",
        "times": "http://ldf.fi/semparl/times/",
        "dct": "http://purl.org/dc/terms/",
        "s_status": "http://ldf.fi/semparl/status/",
        "event": "http://ldf.fi/semparl/events/",
        "prov": "http://www.w3.org/ns/prov#",
        "crm": "http://erlangen-crm.org/current/",
        "gvp": "http://vocab.getty.edu/ontology#",
        "distances": "http://ldf.fi/semparl/distances/",
        "wgs84": "http://www.w3.org/2003/01/geo/wgs84_pos#",
        "ammo": "http://ldf.fi/ammo/",
        "gn": "http://www.geonames.org/ontology#",
        "speeches": "http://ldf.fi/semparl/speeches/",
        "groups": "http://ldf.fi/semparl/groups/",
        "ent": "http://www.w3.org/ns/entailment/",
        "label": "http://ldf.fi/semparl/labels/",
        "people": "http://ldf.fi/semparl/people/",
        "ldf": "http://ldf.fi/schema/ldf/",
        "eks-scheme": "http://ldf.fi/schema/eks/",
        "xl": "http://www.w3.org/2008/05/skos-xl#",
        "bioc": "http://ldf.fi/schema/bioc/",
        "rdf": "http://www.w3.org/1999/02/22-rdf-syntax-ns#",
        "schema1": "http://schema.org/",
        "speech": "http://ldf.fi/semparl/speeches/",
        "natbib": "https://kansallisbiografia.fi/kansallisbiografia/henkilo/",
        "dc": "http://purl.org/dc/elements/1.1/",
        "publications": "http://ldf.fi/semparl/publications/",
        "frbroo": "http://erlangen-crm.org/efrbroo/",
        "@vocab": "http://ldf.fi/eks/"
    }
}