{
    "@id": "people:p911324",
    "bioc:has_family_relation": {
        "@id": "ns1:p1236515196885504744"
    },
    "skos:hiddenLabel": {
        "@language": "fi",
        "@value": "Ramsay, August"
    },
    "sch:relatedLink": {
        "@id": "mps:911324.aspx"
    },
    "semparl:representative_period": {
        "@id": "times:t_1919-04-01_1919-04-01_1922-09-04_1922-09-04"
    },
    "semparl:occupation_text": {
        "@language": "fi",
        "@value": "filosofian tohtori, todellinen valtioneuvos"
    },
    "semparl:end_of_representative_period_text": "04.09.1922",
    "semparl:end_of_representative_period": {
        "@id": "times:t___1922-09-04_1922-09-04"
    },
    "bioc:has_occupation": [
        {
            "@id": "occupations:o1674"
        },
        {
            "@id": "occupations:o233"
        }
    ],
    "semparl:has_party_membership": {
        "@id": "event:p2968341938499734131"
    },
    "crm:P100i_died_in": {
        "@id": "event:d911324"
    },
    "xl:prefLabel": {
        "@id": "label:l2440092650418000867"
    },
    "dct:source": {
        "@id": "https://avoindata.eduskunta.fi/api/v1/tables/MemberOfParliament/rows?perPage=10&page=0&columnName=personId&columnValue=911324"
    },
    "semparl:sortingLabel": "ramsay august",
    "bioc:has_gender": {
        "@id": "sch:Male"
    },
    "crm:P98i_was_born": {
        "@id": "event:b911324"
    },
    "sch:image": [
        {
            "@id": "http://commons.wikimedia.org/wiki/Special:FilePath/Das%20Fotoalbum%20f%C3%BCr%20Weierstra%C3%9F%20046%20%28August%20Ramsay%29.jpg"
        },
        {
            "@id": "http://commons.wikimedia.org/wiki/Special:FilePath/ARamsay.jpg"
        }
    ],
    "sch:sameAs": [
        {
            "@id": "mps:911324.aspx"
        },
        {
            "@id": "viaf:29910937"
        },
        {
            "@id": "natbib:3336"
        },
        {
            "@id": "https://fi.wikipedia.org/wiki/August_Ramsay"
        },
        {
            "@id": "https://commons.wikimedia.org/wiki/Category:August_Ramsay"
        },
        {
            "@id": "wd:Q6163504"
        },
        {
            "@id": "finaf:000056391"
        },
        {
            "@id": "http://biografiasampo.fi/henkilo/p943"
        }
    ],
    "semparl:has_education": [
        {
            "@id": "event:e3202990564492828122"
        },
        {
            "@id": "event:e1787788236021221367"
        },
        {
            "@id": "event:e1104461087554425536"
        },
        {
            "@id": "event:e2687387542283481415"
        },
        {
            "@id": "event:e2180741313483564809"
        }
    ],
    "bioc:bearer_of": [
        {
            "@id": "event:e2669102886263733512"
        },
        {
            "@id": "event:e1134719933305801170"
        },
        {
            "@id": "event:e1986354184717817033"
        },
        {
            "@id": "event:e2535669994729346226"
        },
        {
            "@id": "event:e1565952321443481032"
        },
        {
            "@id": "event:e5005349574220669911"
        },
        {
            "@id": "event:e1127229441018247165"
        },
        {
            "@id": "event:e3377539035938983171"
        },
        {
            "@id": "event:e2042058954087905106"
        },
        {
            "@id": "event:e1746698070049142578"
        },
        {
            "@id": "event:e1667116558840362821"
        },
        {
            "@id": "event:e4923641935982874865"
        },
        {
            "@id": "event:e5290552407446057131"
        },
        {
            "@id": "event:e1671655339615614007"
        },
        {
            "@id": "event:e5920786618519144932"
        },
        {
            "@id": "event:e1363833420358052993"
        },
        {
            "@id": "event:e1166840314077684541"
        },
        {
            "@id": "event:e2672804684743140830"
        },
        {
            "@id": "event:e1772892015260951387"
        },
        {
            "@id": "event:e2023526253227723054"
        },
        {
            "@id": "event:e7222762097437191145"
        },
        {
            "@id": "event:e1820553861811043975"
        },
        {
            "@id": "event:e3129515194182090389"
        },
        {
            "@id": "event:e7140147625535901186"
        },
        {
            "@id": "event:e1290886766437910084"
        },
        {
            "@id": "event:e3351277962150386637"
        },
        {
            "@id": "event:e3211298390626250782"
        },
        {
            "@id": "event:e1001241740787401049"
        },
        {
            "@id": "event:e2358466067054495245"
        },
        {
            "@id": "event:e1986880173908392117"
        },
        {
            "@id": "event:e2284217908354786389"
        },
        {
            "@id": "event:e1750976204451926183"
        },
        {
            "@id": "event:e1889116481777891398"
        },
        {
            "@id": "event:e3029286253032588862"
        },
        {
            "@id": "event:e1512512129415058879"
        },
        {
            "@id": "event:e2183261945500924312"
        },
        {
            "@id": "event:e2910543137954575918"
        },
        {
            "@id": "event:e3178709066479554156"
        },
        {
            "@id": "event:e2485041702743453858"
        },
        {
            "@id": "event:e6211009521705354019"
        },
        {
            "@id": "event:e1149968111202623248"
        },
        {
            "@id": "event:e2933040936351045125"
        },
        {
            "@id": "event:e3333104223620166425"
        },
        {
            "@id": "event:e2053158439010682351"
        },
        {
            "@id": "event:e5455266807701799571"
        },
        {
            "@id": "event:e2382074358690116705"
        },
        {
            "@id": "event:e8405770553207905708"
        },
        {
            "@id": "event:e2275151887470571499"
        },
        {
            "@id": "event:e2306486097951625990"
        },
        {
            "@id": "event:e2150318776214735085"
        },
        {
            "@id": "event:e2270014656062742190"
        },
        {
            "@id": "event:e2932203817176724935"
        },
        {
            "@id": "event:e5079988811888662827"
        },
        {
            "@id": "event:e3127856636355034753"
        },
        {
            "@id": "event:e7410818319566769626"
        },
        {
            "@id": "event:e2286807849273107621"
        }
    ],
    "@type": "bioc:Person",
    "skos:prefLabel": {
        "@language": "fi",
        "@value": "Ramsay, August (1859-1943)"
    },
    "semparl:party": {
        "@id": "groups:Q845537"
    },
    "semparl:id": "911324",
    "@context": {
        "owl": "http://www.w3.org/2002/07/owl#",
        "skos": "http://www.w3.org/2004/02/skos/core#",
        "nif": "http://persistence.uni-leipzig.org/nlp2rdf/ontologies/nif-core#",
        "eks": "http://ldf.fi/eks/",
        "ns1": "http://ldf.fi/semparl/relations/",
        "spls": "http://ldf.fi/schema/semparl/linguistics/",
        "twitter": "https://twitter.com/",
        "yso": "http://www.yso.fi/onto/yso/",
        "dcterms": "http://purl.org/dc/terms/",
        "sch": "http://schema.org/",
        "text": "http://jena.apache.org/text#",
        "spatial": "http://jena.apache.org/spatial#",
        "portal": "http://ldf.fi/schema/parliamentsampo-portal/",
        "foaf": "http://xmlns.com/foaf/0.1/",
        "item": "http://ldf.fi/semparl/items/",
        "void": "http://rdfs.org/ns/void#",
        "committees": "http://ldf.fi/semparl/groups/committees/",
        "eterms": "http://ldf.fi/semparl/times/electoral-terms/",
        "ekss": "http://ldf.fi/schema/eks/",
        "viaf": "https://viaf.org/viaf/",
        "geo1": "http://www.w3.org/2003/01/geo/wgs84_pos#",
        "mps": "https://www.eduskunta.fi/FI/kansanedustajat/Sivut/",
        "external": "http://ldf.fi/semparl/external/",
        "geosparql": "http://www.opengis.net/ont/geosparql#",
        "yle": "https://yle.fi/aihe/t/",
        "semparl_linguistics": "http://ldf.fi/schema/semparl/linguistics/",
        "sps": "http://ldf.fi/semparl/speeches/",
        "semparls": "http://ldf.fi/schema/semparl/",
        "semparl": "http://ldf.fi/schema/semparl/",
        "finaf": "http://urn.fi/URN:NBN:fi:au:finaf:",
        "roles": "http://ldf.fi/semparl/roles/",
        "xsd": "http://www.w3.org/2001/XMLSchema#",
        "districts": "http://ldf.fi/semparl/groups/districts/",
        "affiliations": "http://ldf.fi/semparl/affiliations/",
        "rdfs": "http://www.w3.org/2000/01/rdf-schema#",
        "occupations": "http://ldf.fi/semparl/occupations/",
        "wd": "http://www.wikidata.org/entity/",
        "geo": "http://www.w3.org/2003/01/geo/wgs84_pos#",
        "sd": "http://www.w3.org/ns/sparql-service-description#",
        "times": "http://ldf.fi/semparl/times/",
        "dct": "http://purl.org/dc/terms/",
        "s_status": "http://ldf.fi/semparl/status/",
        "event": "http://ldf.fi/semparl/events/",
        "prov": "http://www.w3.org/ns/prov#",
        "crm": "http://erlangen-crm.org/current/",
        "gvp": "http://vocab.getty.edu/ontology#",
        "distances": "http://ldf.fi/semparl/distances/",
        "wgs84": "http://www.w3.org/2003/01/geo/wgs84_pos#",
        "ammo": "http://ldf.fi/ammo/",
        "gn": "http://www.geonames.org/ontology#",
        "speeches": "http://ldf.fi/semparl/speeches/",
        "groups": "http://ldf.fi/semparl/groups/",
        "ent": "http://www.w3.org/ns/entailment/",
        "label": "http://ldf.fi/semparl/labels/",
        "people": "http://ldf.fi/semparl/people/",
        "ldf": "http://ldf.fi/schema/ldf/",
        "eks-scheme": "http://ldf.fi/schema/eks/",
        "xl": "http://www.w3.org/2008/05/skos-xl#",
        "bioc": "http://ldf.fi/schema/bioc/",
        "rdf": "http://www.w3.org/1999/02/22-rdf-syntax-ns#",
        "schema1": "http://schema.org/",
        "speech": "http://ldf.fi/semparl/speeches/",
        "natbib": "https://kansallisbiografia.fi/kansallisbiografia/henkilo/",
        "dc": "http://purl.org/dc/elements/1.1/",
        "publications": "http://ldf.fi/semparl/publications/",
        "frbroo": "http://erlangen-crm.org/efrbroo/",
        "@vocab": "http://ldf.fi/eks/"
    }
}