{
    "@id": "people:p291",
    "semparl:extra_info": "Vuoden puhuja 1985",
    "semparl:authored": [
        {
            "@id": "publications:b3075419401830203563"
        },
        {
            "@id": "publications:b2617794954923410539"
        },
        {
            "@id": "publications:b2417739324372986332"
        },
        {
            "@id": "publications:b2071085301876963621"
        }
    ],
    "skos:hiddenLabel": {
        "@language": "fi",
        "@value": "Uosukainen, Riitta Maria"
    },
    "sch:relatedLink": {
        "@id": "mps:291.aspx"
    },
    "semparl:representative_period": {
        "@id": "times:t_1983-03-26_1983-03-26_2003-03-18_2003-03-18"
    },
    "semparl:occupation_text": {
        "@language": "fi",
        "@value": "filosofian lisensiaatti, lehtori"
    },
    "semparl:end_of_representative_period_text": "18.03.2003",
    "semparl:end_of_representative_period": {
        "@id": "times:t___2003-03-18_2003-03-18"
    },
    "bioc:has_occupation": [
        {
            "@id": "occupations:o48"
        },
        {
            "@id": "occupations:o107"
        }
    ],
    "semparl:has_party_membership": {
        "@id": "event:p1994392494040668448"
    },
    "xl:altLabel": {
        "@id": "label:l1276128811834833767"
    },
    "xl:prefLabel": {
        "@id": "label:l2191048512312609993"
    },
    "dct:source": {
        "@id": "https://avoindata.eduskunta.fi/api/v1/tables/MemberOfParliament/rows?perPage=10&page=0&columnName=personId&columnValue=291"
    },
    "semparl:sortingLabel": "uosukainen riitta",
    "bioc:has_gender": {
        "@id": "sch:Female"
    },
    "crm:P98i_was_born": {
        "@id": "event:b291"
    },
    "sch:image": {
        "@id": "http://commons.wikimedia.org/wiki/Special:FilePath/Riitta%20Uosukainen.jpg"
    },
    "sch:sameAs": [
        {
            "@id": "mps:291.aspx"
        },
        {
            "@id": "viaf:8623166"
        },
        {
            "@id": "natbib:4083"
        },
        {
            "@id": "https://fi.wikipedia.org/wiki/Riitta_Uosukainen"
        },
        {
            "@id": "https://commons.wikimedia.org/wiki/Category:Riitta_Uosukainen"
        },
        {
            "@id": "wd:Q438744"
        },
        {
            "@id": "finaf:000078948"
        },
        {
            "@id": "http://biografiasampo.fi/henkilo/p5872"
        }
    ],
    "semparl:has_education": [
        {
            "@id": "event:e1456697978633682010"
        },
        {
            "@id": "event:e5562905719412550000"
        },
        {
            "@id": "event:e1893092115679672037"
        },
        {
            "@id": "event:e7871369840118707072"
        },
        {
            "@id": "event:e1825453887464420204"
        },
        {
            "@id": "event:e2149644563279886039"
        }
    ],
    "bioc:bearer_of": [
        {
            "@id": "event:e2941635566901118959"
        },
        {
            "@id": "event:e1223495903031185099"
        },
        {
            "@id": "event:e2319677573630534802"
        },
        {
            "@id": "event:e2658352297534117974"
        },
        {
            "@id": "event:e2832044779952167507"
        },
        {
            "@id": "event:e2403825460283788949"
        },
        {
            "@id": "event:e3015467461417795315"
        },
        {
            "@id": "event:e1948325531155070077"
        },
        {
            "@id": "event:e9570652084444745127"
        },
        {
            "@id": "event:e5818830696575518101"
        },
        {
            "@id": "event:e1980171527522320391"
        },
        {
            "@id": "event:e1706622306375292140"
        },
        {
            "@id": "event:e5610106847518661688"
        },
        {
            "@id": "event:e6961565762441228964"
        },
        {
            "@id": "event:e2887546984146806384"
        },
        {
            "@id": "event:e2784274451383307122"
        },
        {
            "@id": "event:e2562857219232833363"
        },
        {
            "@id": "event:e1505212689724855655"
        },
        {
            "@id": "event:e2070988463164352241"
        },
        {
            "@id": "event:e6360434664343563083"
        },
        {
            "@id": "event:e1511733858057451573"
        },
        {
            "@id": "event:e2256894412190871676"
        },
        {
            "@id": "event:e8282790930827649044"
        },
        {
            "@id": "event:e1373745328522601489"
        },
        {
            "@id": "event:e8255896161331575764"
        },
        {
            "@id": "event:e2499541753200431286"
        },
        {
            "@id": "event:e3320288539524123120"
        },
        {
            "@id": "event:e6162063842530412227"
        },
        {
            "@id": "event:e1507380222325024023"
        },
        {
            "@id": "event:e3199335235111896085"
        },
        {
            "@id": "event:e3199149242949572239"
        },
        {
            "@id": "event:e3160167846903606238"
        },
        {
            "@id": "event:e8607501392403711460"
        },
        {
            "@id": "event:e1428198040677490083"
        },
        {
            "@id": "event:e3340073085458075817"
        },
        {
            "@id": "event:e1673026237661385176"
        },
        {
            "@id": "event:e3050206314562068443"
        },
        {
            "@id": "event:e2334983403281736808"
        },
        {
            "@id": "event:e1311177141291329543"
        },
        {
            "@id": "event:e3203737040985544460"
        },
        {
            "@id": "event:e1387031218706220671"
        },
        {
            "@id": "event:e7781661072632799488"
        },
        {
            "@id": "event:e2032668100720343959"
        },
        {
            "@id": "event:e9345523107817709582"
        },
        {
            "@id": "event:e5495885300888132196"
        },
        {
            "@id": "event:e1943632254915456821"
        },
        {
            "@id": "event:e4296724331821027818"
        },
        {
            "@id": "event:e1492582351050377348"
        },
        {
            "@id": "event:e1469725956193471629"
        },
        {
            "@id": "event:e2837304644016483225"
        },
        {
            "@id": "event:e8374915790799658393"
        },
        {
            "@id": "event:e6753840209327638884"
        },
        {
            "@id": "event:e9610305238225585189"
        },
        {
            "@id": "event:e1791637697854257615"
        },
        {
            "@id": "event:e2422058805464467227"
        },
        {
            "@id": "event:e2936368711761517150"
        },
        {
            "@id": "event:e1587060023355211167"
        },
        {
            "@id": "event:e2872642502153821566"
        },
        {
            "@id": "event:e1904441959826634636"
        },
        {
            "@id": "event:e1263231464197322834"
        },
        {
            "@id": "event:e2383774783750021460"
        },
        {
            "@id": "event:e3371069789934867915"
        }
    ],
    "@type": "bioc:Person",
    "skos:prefLabel": {
        "@language": "fi",
        "@value": "Uosukainen, Riitta (1942-)"
    },
    "skos:altLabel": {
        "@language": "fi",
        "@value": "Uosukainen, Riitta Maria"
    },
    "semparl:party": {
        "@id": "groups:Q304191"
    },
    "semparl:id": "291",
    "@context": {
        "owl": "http://www.w3.org/2002/07/owl#",
        "skos": "http://www.w3.org/2004/02/skos/core#",
        "nif": "http://persistence.uni-leipzig.org/nlp2rdf/ontologies/nif-core#",
        "eks": "http://ldf.fi/eks/",
        "ns1": "http://ldf.fi/semparl/relations/",
        "spls": "http://ldf.fi/schema/semparl/linguistics/",
        "twitter": "https://twitter.com/",
        "yso": "http://www.yso.fi/onto/yso/",
        "dcterms": "http://purl.org/dc/terms/",
        "sch": "http://schema.org/",
        "text": "http://jena.apache.org/text#",
        "spatial": "http://jena.apache.org/spatial#",
        "portal": "http://ldf.fi/schema/parliamentsampo-portal/",
        "foaf": "http://xmlns.com/foaf/0.1/",
        "item": "http://ldf.fi/semparl/items/",
        "void": "http://rdfs.org/ns/void#",
        "committees": "http://ldf.fi/semparl/groups/committees/",
        "eterms": "http://ldf.fi/semparl/times/electoral-terms/",
        "ekss": "http://ldf.fi/schema/eks/",
        "viaf": "https://viaf.org/viaf/",
        "geo1": "http://www.w3.org/2003/01/geo/wgs84_pos#",
        "mps": "https://www.eduskunta.fi/FI/kansanedustajat/Sivut/",
        "external": "http://ldf.fi/semparl/external/",
        "geosparql": "http://www.opengis.net/ont/geosparql#",
        "yle": "https://yle.fi/aihe/t/",
        "semparl_linguistics": "http://ldf.fi/schema/semparl/linguistics/",
        "sps": "http://ldf.fi/semparl/speeches/",
        "semparls": "http://ldf.fi/schema/semparl/",
        "semparl": "http://ldf.fi/schema/semparl/",
        "finaf": "http://urn.fi/URN:NBN:fi:au:finaf:",
        "roles": "http://ldf.fi/semparl/roles/",
        "xsd": "http://www.w3.org/2001/XMLSchema#",
        "districts": "http://ldf.fi/semparl/groups/districts/",
        "affiliations": "http://ldf.fi/semparl/affiliations/",
        "rdfs": "http://www.w3.org/2000/01/rdf-schema#",
        "occupations": "http://ldf.fi/semparl/occupations/",
        "wd": "http://www.wikidata.org/entity/",
        "geo": "http://www.w3.org/2003/01/geo/wgs84_pos#",
        "sd": "http://www.w3.org/ns/sparql-service-description#",
        "times": "http://ldf.fi/semparl/times/",
        "dct": "http://purl.org/dc/terms/",
        "s_status": "http://ldf.fi/semparl/status/",
        "event": "http://ldf.fi/semparl/events/",
        "prov": "http://www.w3.org/ns/prov#",
        "crm": "http://erlangen-crm.org/current/",
        "gvp": "http://vocab.getty.edu/ontology#",
        "distances": "http://ldf.fi/semparl/distances/",
        "wgs84": "http://www.w3.org/2003/01/geo/wgs84_pos#",
        "ammo": "http://ldf.fi/ammo/",
        "gn": "http://www.geonames.org/ontology#",
        "speeches": "http://ldf.fi/semparl/speeches/",
        "groups": "http://ldf.fi/semparl/groups/",
        "ent": "http://www.w3.org/ns/entailment/",
        "label": "http://ldf.fi/semparl/labels/",
        "people": "http://ldf.fi/semparl/people/",
        "ldf": "http://ldf.fi/schema/ldf/",
        "eks-scheme": "http://ldf.fi/schema/eks/",
        "xl": "http://www.w3.org/2008/05/skos-xl#",
        "bioc": "http://ldf.fi/schema/bioc/",
        "rdf": "http://www.w3.org/1999/02/22-rdf-syntax-ns#",
        "schema1": "http://schema.org/",
        "speech": "http://ldf.fi/semparl/speeches/",
        "natbib": "https://kansallisbiografia.fi/kansallisbiografia/henkilo/",
        "dc": "http://purl.org/dc/elements/1.1/",
        "publications": "http://ldf.fi/semparl/publications/",
        "frbroo": "http://erlangen-crm.org/efrbroo/",
        "@vocab": "http://ldf.fi/eks/"
    }
}